Metadata-Version: 2.1
Name: LiliDB
Version: 1.0.2
Summary: Key-Value database library, small and easy to use.
Home-page: https://github.com/ZSendokame/LiliDB
Author: ZSendokame
License: MIT license
License-File: LICENSE
